README.md
setup.py
qyt_devnet/__init__.py
qyt_devnet/qyt_cisco_cmd.py
qyt_devnet/qyt_cisco_snmp.py
qyt_devnet/qyt_cmd.py
qyt_devnet/qyt_snmp.py
qyt_devnet.egg-info/PKG-INFO
qyt_devnet.egg-info/SOURCES.txt
qyt_devnet.egg-info/dependency_links.txt
qyt_devnet.egg-info/requires.txt
qyt_devnet.egg-info/top_level.txt
qyt_devnet/modules/__init__.py
qyt_devnet/modules/snmp_v2_get.py
qyt_devnet/modules/snmp_v2_getbulk.py
qyt_devnet/modules/snmp_v2_getnext.py