Metadata-Version: 1.2
Name: qyt-devnet
Version: 1.0.0
Summary: 乾颐堂网络设备自动化封装
Home-page: https://github.com/collinsctk/DevNet_Huawei
Author: cq_bomb
Author-email: collinsctk@qytang.com
License: GNU General Public License v3.0
Platform: UNKNOWN
Requires-Python: >=3.6
